tesla_fleet_api/__init__.py
tesla_fleet_api/const.py
tesla_fleet_api/exceptions.py
tesla_fleet_api/py.typed
tesla_fleet_api/tesla/__init__.py
tesla_fleet_api/tesla/bluetooth.py
tesla_fleet_api/tesla/charging.py
tesla_fleet_api/tesla/energysite.py
tesla_fleet_api/tesla/fleet.py
tesla_fleet_api/tesla/oauth.py
tesla_fleet_api/tesla/partner.py
tesla_fleet_api/tesla/tesla.py
tesla_fleet_api/tesla/user.py
tesla_fleet_api/tesla/vehicle/__init__.py
tesla_fleet_api/tesla/vehicle/bluetooth.py
tesla_fleet_api/tesla/vehicle/commands.py
tesla_fleet_api/tesla/vehicle/fleet.py
tesla_fleet_api/tesla/vehicle/signed.py
tesla_fleet_api/tesla/vehicle/vehicle.py
tesla_fleet_api/tesla/vehicle/vehicles.py
tesla_fleet_api/tesla/vehicle/proto/__init__.py
tesla_fleet_api/tesla/vehicle/proto/__init__.pyi
tesla_fleet_api/tesla/vehicle/proto/car_server_pb2.py
tesla_fleet_api/tesla/vehicle/proto/car_server_pb2.pyi
tesla_fleet_api/tesla/vehicle/proto/common_pb2.py
tesla_fleet_api/tesla/vehicle/proto/common_pb2.pyi
tesla_fleet_api/tesla/vehicle/proto/errors_pb2.py
tesla_fleet_api/tesla/vehicle/proto/errors_pb2.pyi
tesla_fleet_api/tesla/vehicle/proto/keys_pb2.py
tesla_fleet_api/tesla/vehicle/proto/keys_pb2.pyi
tesla_fleet_api/tesla/vehicle/proto/managed_charging_pb2.py
tesla_fleet_api/tesla/vehicle/proto/managed_charging_pb2.pyi
tesla_fleet_api/tesla/vehicle/proto/signatures_pb2.py
tesla_fleet_api/tesla/vehicle/proto/signatures_pb2.pyi
tesla_fleet_api/tesla/vehicle/proto/universal_message_pb2.py
tesla_fleet_api/tesla/vehicle/proto/universal_message_pb2.pyi
tesla_fleet_api/tesla/vehicle/proto/vcsec_pb2.py
tesla_fleet_api/tesla/vehicle/proto/vcsec_pb2.pyi
tesla_fleet_api/tesla/vehicle/proto/vehicle_pb2.py
tesla_fleet_api/tesla/vehicle/proto/vehicle_pb2.pyi
tesla_fleet_api/teslemetry/__init__.py
tesla_fleet_api/teslemetry/teslemetry.py
tesla_fleet_api/teslemetry/vehicles.py
tesla_fleet_api/tessie/__init__.py
tesla_fleet_api/tessie/tessie.py
tesla_fleet_api/tessie/vehicles.py
tesla_fleet_api-1.4.0.dist-info/licenses/LICENSE
tesla_fleet_api-1.4.0.dist-info/METADATA
tesla_fleet_api-1.4.0.dist-info/WHEEL
tesla_fleet_api-1.4.0.dist-info/top_level.txt
tesla_fleet_api-1.4.0.dist-info/RECORD
