Metadata-Version: 2.4
Name: tesla_fleet_api
Version: 1.4.0
Summary: Tesla Fleet API library for Python
Author-email: Brett Adams <hello@teslemetry.com>
License-Expression: Apache-2.0
Project-URL: Homepage, https://github.com/Teslemetry/python-tesla-fleet-api
Classifier: Development Status :: 5 - Production/Stable
Classifier: Programming Language :: Python :: 3
Classifier: Operating System :: OS Independent
Requires-Python: >=3.10
License-File: LICENSE
Requires-Dist: aiohttp
Requires-Dist: aiofiles
Requires-Dist: aiolimiter
Requires-Dist: cryptography
Requires-Dist: protobuf
Requires-Dist: bleak
Requires-Dist: bleak-retry-connector
Dynamic: license-file
